{
"title": "JSON Request Schema",
"description": "JSON Request Schema of transaction.update.supplyChain.setWarehouseInboundOrderDetail (version 1)",
"type": "object",
"properties": {
    "metadata": {
        "type": "object",
        "properties": {
            "API": {
                "type": "object",
                "properties": {
                    "key": {
                        "type": "string",
                        "enum": [ "transaction.update.supplyChain.setWarehouseInboundOrderDetail" ]
                        },
                    "version": {
                        "type": [ "integer", "string" ],
                        "minimum": 1,
                        "minLength": 1
                        }
                    },
                "required": [
                    "key",
                    "version"
                    ]
                }
            },
        "required": [
            "API"
            ]
        },
    "data": {
        "type": "object",
        "properties": {
            "recordID" : {
                "type": "integer",
                "minimum": 1,
                "maximum": 9223372036854775807
                },
            "entities" : {
                "type": "object",
                "properties": {
                    "warehouseInboundOrder_RefID": {
                        "type": [ "integer", "null" ],
                        "minimum": 1,
                        "maximum": 9223372036854775807
                        },
                    "referenceDocument_RefID": {
                        "type": [ "integer", "null" ],
                        "minimum": 1,
                        "maximum": 9223372036854775807
                        },
                    "product_RefID": {
                        "type": [ "integer", "null" ],
                        "minimum": 1,
                        "maximum": 9223372036854775807
                        },
                    "quantity": {
                        "type": [ "number", "null" ],
                        "minimum": 0
                        },
                    "quantityUnit_RefID": {
                        "type": [ "integer", "null" ],
                        "minimum": 1,
                        "maximum": 9223372036854775807
                        },
                    "productUnitPriceCurrency_RefID": {
                        "type": [ "integer", "null" ],
                        "minimum": 1,
                        "maximum": 9223372036854775807
                        },
                    "productUnitPriceCurrencyValue": {
                        "type": [ "number", "null" ],
                        "minimum": 0
                        },
                    "productUnitPriceCurrencyExchangeRate": {
                        "type": [ "number", "null" ],
                        "minimum": 0
                        },
                    "remarks": {
                        "type": [ "string", "null" ],
                        "minLength": 1,
                        "maxLength": 512
                        }
                    },
                "required": [
                    "warehouseInboundOrder_RefID",
                    "referenceDocument_RefID",
                    "product_RefID",
                    "quantity",
                    "quantityUnit_RefID",
                    "productUnitPriceCurrency_RefID",
                    "productUnitPriceCurrencyValue",
                    "productUnitPriceCurrencyExchangeRate",
                    "remarks"
                    ]
                }
            },
        "required": [
            "recordID",
            "entities"
            ]
        }
    },
"required": [
    "metadata",
    "data"
    ]
}